{
  "version": 2,
  "projects": [
    {
      "fieldConfig": {},
      "defaultName": "",
      "templates": [],
      "excludedNotes": [],
      "isDefault": false,
      "dataSource": {
        "kind": "folder",
        "config": {
          "path": "Projects - Demo Project",
          "recursive": false
        }
      },
      "newNotesFolder": "",
      "views": [
        {
          "config": {
            "fieldConfig": {
              "name": {
                "width": 360
              },
              "path": {
                "hide": true
              }
            }
          },
          "filter": {
            "conjunction": "and",
            "conditions": []
          },
          "colors": {
            "conditions": []
          },
          "sort": {
            "criteria": []
          },
          "name": "Table",
          "id": "daacfe65-0ba4-4b92-aac2-ef70805ae3f9",
          "type": "table"
        },
        {
          "config": {
            "groupByField": "status",
            "orderSyncField": "weight"
          },
          "filter": {
            "conjunction": "and",
            "conditions": []
          },
          "colors": {
            "conditions": []
          },
          "sort": {
            "criteria": []
          },
          "name": "Board",
          "id": "2c4b6634-e610-41a7-b1d0-c16eb9ffcd58",
          "type": "board"
        },
        {
          "config": {
            "interval": "month",
            "dateField": "due",
            "checkField": "published"
          },
          "filter": {
            "conjunction": "and",
            "conditions": []
          },
          "colors": {
            "conditions": []
          },
          "sort": {
            "criteria": []
          },
          "name": "Calendar",
          "id": "17a83708-d42d-4bcf-aa64-1dd5a3d8d207",
          "type": "calendar"
        },
        {
          "config": {
            "coverField": "image"
          },
          "filter": {
            "conjunction": "and",
            "conditions": []
          },
          "colors": {
            "conditions": []
          },
          "sort": {
            "criteria": []
          },
          "name": "Gallery",
          "id": "a0571637-b10b-45bc-9a66-83fc83977892",
          "type": "gallery"
        }
      ],
      "name": "Demo project",
      "id": "580f19c3-c136-45b8-8606-1ddc0f6ecca4",
      "path": "Projects - Demo Project"
    }
  ],
  "archives": [],
  "preferences": {
    "projectSizeLimit": 1000,
    "frontmatter": {
      "quoteStrings": "PLAIN"
    },
    "locale": {
      "firstDayOfWeek": "default"
    },
    "commands": [],
    "linkBehavior": "open-editor"
  }
}